google_cloud_ndbm/__init__.py
google_cloud_ndbm/flask.py
google_cloud_ndbm-1.0.dist-info/LICENSE
google_cloud_ndbm-1.0.dist-info/METADATA
google_cloud_ndbm-1.0.dist-info/WHEEL
google_cloud_ndbm-1.0.dist-info/top_level.txt
google_cloud_ndbm-1.0.dist-info/RECORD
