Metadata-Version: 2.1
Name: google-cloud-ndbm
Version: 1.0
Summary: Wrapper for google.cloud.ndb
Home-page: https://github.com/vb64/google.cloud.ndbm
Author: Vitaly Bogomolov
Author-email: mail@vitaly-bogomolov.ru
License: UNKNOWN
Project-URL: Bug Tracker, https://github.com/vb64/google.cloud.ndbm/issues
Platform: UNKNOWN
Classifier: Programming Language :: Python
Classifier: License :: OSI Approved :: MIT License
Classifier: Operating System :: OS Independent
Requires-Dist: google-cloud-ndb (==1.11.2)
